{
  "db_name": "PostgreSQL",
  "query": "\n        SELECT payment_intent_id, order_id, provider_key, status\n        FROM payment.payment_intent\n        WHERE payment_intent_id = $1\n        ",
  "describe": {
    "columns": [
      {
        "ordinal": 0,
        "name": "payment_intent_id",
        "type_info": "Uuid"
      },
      {
        "ordinal": 1,
        "name": "order_id",
        "type_info": "Uuid"
      },
      {
        "ordinal": 2,
        "name": "provider_key",
        "type_info": "Text"
      },
      {
        "ordinal": 3,
        "name": "status",
        "type_info": "Text"
      }
    ],
    "parameters": {
      "Left": [
        "Uuid"
      ]
    },
    "nullable": [
      false,
      true,
      false,
      false
    ]
  },
  "hash": "6e632daf8ef4586ce9577e0ec8c1463872794b796dfcba13f62092e06b59eec9"
}
